{
  "db_name": "PostgreSQL",
  "query": "\n            DELETE FROM institution\n            WHERE id = $1\n            RETURNING *\n            ",
  "describe": {
    "columns": [
      {
        "ordinal": 0,
        "name": "id",
        "type_info": "Uuid"
      },
      {
        "ordinal": 1,
        "name": "created_at",
        "type_info": "Timestamptz"
      },
      {
        "ordinal": 2,
        "name": "updated_at",
        "type_info": "Timestamptz"
      },
      {
        "ordinal": 3,
        "name": "name",
        "type_info": "Varchar"
      }
    ],
    "parameters": {
      "Left": [
        "Uuid"
      ]
    },
    "nullable": [
      false,
      false,
      false,
      false
    ]
  },
  "hash": "e559b8d294079838eb92abc891033b105a6b5d83245964360f27f1231ce1942a"
}
